cloudio/__init__.py
cloudio/endpoint/__init__.py
cloudio/endpoint/endpoint.py
cloudio/endpoint/properties_endpoint_configuration.py
cloudio/endpoint/topicuuid.py
cloudio/endpoint/version.py
cloudio/endpoint/attribute/__init__.py
cloudio/endpoint/attribute/attribute.py
cloudio/endpoint/attribute/constraint.py
cloudio/endpoint/attribute/type.py
cloudio/endpoint/exception/__init__.py
cloudio/endpoint/exception/cloudio_modification_exception.py
cloudio/endpoint/exception/invalid_cloudio_attribute_exception.py
cloudio/endpoint/exception/invalid_cloudio_attribute_type_exception.py
cloudio/endpoint/exception/invalid_property_exception.py
cloudio/endpoint/interface/__init__.py
cloudio/endpoint/interface/attribute_container.py
cloudio/endpoint/interface/attribute_listener.py
cloudio/endpoint/interface/message_format.py
cloudio/endpoint/interface/named_item.py
cloudio/endpoint/interface/node_container.py
cloudio/endpoint/interface/object_container.py
cloudio/endpoint/interface/unique_identifiable.py
cloudio/endpoint/interface/uuid.py
cloudio/endpoint/message_format/__init__.py
cloudio/endpoint/message_format/cbor_format.py
cloudio/endpoint/message_format/factory.py
cloudio/endpoint/message_format/generic_format.py
cloudio/endpoint/message_format/json_format.py
cloudio/endpoint/node/__init__.py
cloudio/endpoint/node/node.py
cloudio/endpoint/object/__init__.py
cloudio/endpoint/object/object.py
cloudio/endpoint/runtime/__init__.py
cloudio/endpoint/runtime/node.py
cloudio/endpoint/runtime/object.py
cloudio/endpoint/transaction/__init__.py
cloudio/endpoint/transaction/transaction.py
cloudio_endpoint_python-2.0.0.dist-info/LICENSE
cloudio_endpoint_python-2.0.0.dist-info/METADATA
cloudio_endpoint_python-2.0.0.dist-info/WHEEL
cloudio_endpoint_python-2.0.0.dist-info/top_level.txt
cloudio_endpoint_python-2.0.0.dist-info/RECORD
