Metadata-Version: 2.1
Name: cloudio-endpoint-python
Version: 2.0.0
Summary: cloud.iO endpoint library
Home-page: https://cloudio.hevs.ch
Author: HES-SO Valais, School of Engineering, Sion
Author-email: thomas.sterren@hevs.ch
License: MIT
Project-URL: Bug Tracker, https://github.com/cloudio-project/cloudio-endpoint-python/issues
Project-URL: Source Code, https://github.com/cloudio-project/cloudio-endpoint-python
Project-URL: Documentation, https://github.com/cloudio-project/cloudio-endpoint-python#cloudio-endpoint-python
Keywords: cloud.iO endpoint library IoT cloud
Classifier: Development Status :: 4 - Beta
Classifier: Intended Audience :: Developers
Classifier: Intended Audience :: Education
Classifier: Intended Audience :: Science/Research
Classifier: Intended Audience :: Information Technology
Classifier: Topic :: Software Development :: Libraries :: Python Modules
Classifier: License :: OSI Approved :: MIT License
Classifier: Programming Language :: Python :: 3.8
Classifier: Programming Language :: Python :: 3.9
Classifier: Operating System :: OS Independent
License-File: LICENSE
Requires-Dist: cloudio-common-python
Requires-Dist: configobj
